LearnHowToPackage_hsr/__init__.py
LearnHowToPackage_hsr/example_module.py
LearnHowToPackage_hsr-0.2.dist-info/LICENSE.txt
LearnHowToPackage_hsr-0.2.dist-info/METADATA
LearnHowToPackage_hsr-0.2.dist-info/WHEEL
LearnHowToPackage_hsr-0.2.dist-info/top_level.txt
LearnHowToPackage_hsr-0.2.dist-info/RECORD
